code_annotations/__init__.py
code_annotations/annotation_errors.py
code_annotations/base.py
code_annotations/cli.py
code_annotations/exceptions.py
code_annotations/find_django.py
code_annotations/find_static.py
code_annotations/generate_docs.py
code_annotations/helpers.py
code_annotations/contrib/config/__init__.py
code_annotations/contrib/config/feature_toggle_annotations.yaml
code_annotations/contrib/config/openedx_events_annotations.yaml
code_annotations/contrib/config/setting_annotations.yaml
code_annotations/contrib/sphinx/extensions/__init__.py
code_annotations/contrib/sphinx/extensions/base.py
code_annotations/contrib/sphinx/extensions/featuretoggles.py
code_annotations/contrib/sphinx/extensions/openedx_events.py
code_annotations/contrib/sphinx/extensions/settings.py
code_annotations/extensions/__init__.py
code_annotations/extensions/base.py
code_annotations/extensions/javascript.py
code_annotations/extensions/python.py
code_annotations/report_templates/html/annotation.tpl
code_annotations/report_templates/html/annotation_data.tpl
code_annotations/report_templates/html/annotation_list.tpl
code_annotations/report_templates/html/base.tpl
code_annotations/report_templates/rst/annotation.tpl
code_annotations/report_templates/rst/annotation_data.tpl
code_annotations/report_templates/rst/annotation_group.tpl
code_annotations/report_templates/rst/annotation_list.tpl
code_annotations/report_templates/rst/base.tpl
code_annotations-2.3.0.dist-info/licenses/LICENSE.txt
code_annotations-2.3.0.dist-info/licenses/NOTICE.txt
code_annotations-2.3.0.dist-info/METADATA
code_annotations-2.3.0.dist-info/WHEEL
code_annotations-2.3.0.dist-info/entry_points.txt
code_annotations-2.3.0.dist-info/top_level.txt
code_annotations-2.3.0.dist-info/RECORD
