Metadata-Version: 2.4
Name: code-annotations
Version: 2.3.0
Summary: Extensible tools for parsing annotations in codebases
Home-page: https://github.com/openedx/code-annotations
Author: edX
Author-email: oscm@edx.org
License: Apache Software License 2.0
Keywords: edx pii code annotations
Classifier: Development Status :: 3 - Alpha
Classifier: Framework :: Django
Classifier: Framework :: Django :: 4.2
Classifier: Framework :: Django :: 5.2
Classifier: Intended Audience :: Developers
Classifier: License :: OSI Approved :: Apache Software License
Classifier: Natural Language :: English
Classifier: Programming Language :: Python
Classifier: Programming Language :: Python :: 3
Classifier: Programming Language :: Python :: 3.11
Classifier: Programming Language :: Python :: 3.12
Requires-Python: >=3.11
License-File: LICENSE.txt
License-File: NOTICE.txt
Requires-Dist: python-slugify
Requires-Dist: stevedore
Requires-Dist: click
Requires-Dist: pyyaml
Requires-Dist: Jinja2
Provides-Extra: django
Requires-Dist: Django>=4.2; extra == "django"
Dynamic: author
Dynamic: author-email
Dynamic: classifier
Dynamic: description
Dynamic: description-content-type
Dynamic: home-page
Dynamic: keywords
Dynamic: license
Dynamic: license-file
Dynamic: provides-extra
Dynamic: requires-dist
Dynamic: requires-python
Dynamic: summary
